Workbook
Name aporte: Reis_Invest!$D$14
Name insira_perfil: Reis_Invest!$C$30
Name patrimonio: Reis_Invest!$D$17
Name qtd_anos: Reis_Invest!$D$15
Name Rendimento_carteira: Reis_Invest!$D$10
Name salario: Reis_Invest!$D$9
Name sugestao_investimento: Reis_Invest!$D$11
Name taxa_mensal: Reis_Invest!$D$16

Sheet Reis_Invest
B8: CONFIGURAÇÕES
B9: Salário | D9: 1000
B10: Rendimento Carteira | D10: 0
B11: Sugestão de Investimento (20% do salário) | D11: =D9*20% -> 200
B13: INVESTIMENTO MENSAL
B14: Quantos investir por mês? | D14: 0
B15: Por quanto tempo (em anos)? | D15: 0
B16: Taxa de rendimento mensal? | D16: 0
B17: Patrimônio acumulado? | D17: =FV(taxa_mensal,(qtd_anos*12),(aporte*-1)) -> 0
B18: Dividendos mensais? | D18: =patrimonio*Rendimento_carteira -> 0
B20: CENÁRIOS FUTUROS | C20: VALOR INVESTIDO | D20: DIVIDENDOS
A21: 2 | B21: Quanto em 2 anos? | C21: =FV($D$16,$A21*12,$D$14*-1) -> 0 | D21: =C21*Rendimento_carteira -> 0
A22: 5 | B22: Quanto em 5 anos? | C22: =FV($D$16,$A22*12,$D$14*-1) -> 0 | D22: =C22*Rendimento_carteira -> 0
A23: 10 | B23: Quanto em 10 anos? | C23: =FV($D$16,$A23*12,$D$14*-1) -> 0 | D23: =C23*Rendimento_carteira -> 0
A24: 20 | B24: Quanto em 20 anos? | C24: =FV($D$16,$A24*12,$D$14*-1) -> 0 | D24: =C24*Rendimento_carteira -> 0
A25: 30 | B25: Quanto em 30 anos? | C25: =FV($D$16,$A25*12,$D$14*-1) -> 0 | D25: =C25*Rendimento_carteira -> 0
B27: SUGESTÕES DE INVESTIMENTOS
C29: Selecione seu perfil
B30: Perfil de Investimento | C30: Moderado
B31: Valor a ser investido por mês | C31: =aporte -> 0
B33: Tipos de Fundos imobiliários (FII's) | C33: Percentual Sugerido | D33: Valores
B34: PAPEL | C34: =IFERROR(VLOOKUP($C$30&"-"&$B34,Tab_apoio!$A:$D,4,0),"Selecione seu perfil") -> 0.32 | D34: =IFERROR((C34*$C$31),"Aguardando Perfil") -> 0
B35: TIJOLO | C35: =IFERROR(VLOOKUP($C$30&"-"&$B35,Tab_apoio!$A:$D,4,0),"Selecione seu perfil") -> 0.35 | D35: =IFERROR((C35*$C$31),"Aguardando Perfil") -> 0
B36: HIBRIDOS | C36: =IFERROR(VLOOKUP($C$30&"-"&$B36,Tab_apoio!$A:$D,4,0),"Selecione seu perfil") -> 0.08 | D36: =IFERROR((C36*$C$31),"Aguardando Perfil") -> 0
B37: FOFs | C37: =IFERROR(VLOOKUP($C$30&"-"&$B37,Tab_apoio!$A:$D,4,0),"Selecione seu perfil") -> 0.05 | D37: =IFERROR((C37*$C$31),"Aguardando Perfil") -> 0
B38: DESENVOLVIMENTO | C38: =IFERROR(VLOOKUP($C$30&"-"&$B38,Tab_apoio!$A:$D,4,0),"Selecione seu perfil") -> 0.1 | D38: =IFERROR((C38*$C$31),"Aguardando Perfil") -> 0
B39: HOTELARIAS | C39: =IFERROR(VLOOKUP($C$30&"-"&$B39,Tab_apoio!$A:$D,4,0),"Selecione seu perfil") -> 0.1 | D39: =IFERROR((C39*$C$31),"Aguardando Perfil") -> 0
B40: Total | D40: =SUM(D34:D39) -> 0

Sheet Tab_apoio
A1: CHAVE COMPOSTA | B1: PERFIL | C1: TIPO DE FII | D1: %
A2: =B2&"-"&$C2 -> Conservador-PAPEL | B2: Conservador | C2: PAPEL | D2: 0.3
A3: =B3&"-"&$C3 -> Conservador-TIJOLO | B3: Conservador | C3: TIJOLO | D3: 0.5
A4: =B4&"-"&$C4 -> Conservador-HIBRIDOS | B4: Conservador | C4: HIBRIDOS | D4: 0.1
A5: =B5&"-"&$C5 -> Conservador-FOFs | B5: Conservador | C5: FOFs | D5: 0.1
A6: =B6&"-"&$C6 -> Conservador-DESENVOLVIMENTO | B6: Conservador | C6: DESENVOLVIMENTO | D6: 0
A7: =B7&"-"&$C7 -> Conservador-HOTELARIAS | B7: Conservador | C7: HOTELARIAS | D7: 0
A8: =B8&"-"&$C2 -> Moderado-PAPEL | B8: Moderado | C8: PAPEL | D8: 0.32
A9: =B9&"-"&$C3 -> Moderado-TIJOLO | B9: Moderado | C9: TIJOLO | D9: 0.35
A10: =B10&"-"&$C4 -> Moderado-HIBRIDOS | B10: Moderado | C10: HIBRIDOS | D10: 0.08
A11: =B11&"-"&$C5 -> Moderado-FOFs | B11: Moderado | C11: FOFs | D11: 0.05
A12: =B12&"-"&$C6 -> Moderado-DESENVOLVIMENTO | B12: Moderado | C12: DESENVOLVIMENTO | D12: 0.1
A13: =B13&"-"&$C7 -> Moderado-HOTELARIAS | B13: Moderado | C13: HOTELARIAS | D13: 0.1
A14: =B14&"-"&$C2 -> Agressivo-PAPEL | B14: Agressivo | C14: PAPEL | D14: 0.5
A15: =B15&"-"&$C3 -> Agressivo-TIJOLO | B15: Agressivo | C15: TIJOLO | D15: 0.1
A16: =B16&"-"&$C4 -> Agressivo-HIBRIDOS | B16: Agressivo | C16: HIBRIDOS | D16: 0.05
A17: =B17&"-"&$C5 -> Agressivo-FOFs | B17: Agressivo | C17: FOFs | D17: 0.05
A18: =B18&"-"&$C6 -> Agressivo-DESENVOLVIMENTO | B18: Agressivo | C18: DESENVOLVIMENTO | D18: 0.2
A19: =B19&"-"&$C7 -> Agressivo-HOTELARIAS | B19: Agressivo | C19: HOTELARIAS | D19: 0.1
